wait4gpu_huyiwen/__init__.py
wait4gpu_huyiwen/__main__.py
wait4gpu_huyiwen/wait4gpu.py
wait4gpu-0.0.1.dist-info/LICENSE
wait4gpu-0.0.1.dist-info/METADATA
wait4gpu-0.0.1.dist-info/WHEEL
wait4gpu-0.0.1.dist-info/top_level.txt
wait4gpu-0.0.1.dist-info/RECORD
