Metadata-Version: 2.1
Name: wait4gpu
Version: 0.0.1
Summary: A simple utility to execute your deep learning scripts when there are enough idle gpus
Author-email: huyiwen <1020030101@qq.com>
Project-URL: Homepage, https://github.com/huyiwen/Wait4GPU
Project-URL: Issues, https://github.com/huyiwen/Wait4GPU/issues
Classifier: Programming Language :: Python :: 3
Classifier: License :: OSI Approved :: MIT License
Classifier: Operating System :: OS Independent
Requires-Python: >=3.6
License-File: LICENSE
